LICENSE.txt
MANIFEST.in
README.rst
setup.py
cva/__init__.py
cva/_version.py
cva/metric.py
cva/model.py
cva/solve.py
cva/view.py
cva.egg-info/PKG-INFO
cva.egg-info/SOURCES.txt
cva.egg-info/dependency_links.txt
cva.egg-info/requires.txt
cva.egg-info/top_level.txt
cva/examples/__init__.py
cva/examples/case01_torus.py
cva/examples/case02_sphere.py
cva/examples/case03_earth.py
cva/examples/case04_cylinder.py
cva/examples/case05_hyperboloid.py
cva/examples/case06_plane.py
cva/examples/case07_sphylinder.py
cva/examples/case08_capped_cylinder.py
cva/examples/case09_moebius.py
cva/examples/case10_brachistochrone_plane_earth.py
cva/examples/case11_brachistochrone_tilted_plane.py
cva/examples/case12_brachistochrone_plane_moon.py
cva/examples/case13_brachistochrone_unit_sphere.py
cva/examples/case14_brachistochrone_hyperboloid.py
cva/examples/case15_earth_latlon.py
cva/examples/case17_spacetime_plane.py
cva/examples/case18_blackhole_geodesic_family.py
cva/examples/case19_collapsing_sphere.py
cva/examples/case20_inflating_sphere.py
cva/examples/case21_sphere_in_r3.py
cva/examples/case22_sphere_in_r4.py
cva/examples/case23_sphere_in_r5.py
cva/examples/case24_sphere_in_r6.py
cva/examples/case25_sphere_in_r7.py
cva/examples/case26_sphere_in_r8.py
cva/test/__init__.py
cva/test/do_tests.py
cva/test/scenario_run_all_examples.py
cva/test/test_metric.py
cva/test/test_metric_schwarzschild.py
cva/test/test_model_capped_cylinder.py
cva/test/test_model_cylinder.py
cva/test/test_model_earth.py
cva/test/test_model_earth_wrapped.py
cva/test/test_model_hyperboloid.py
cva/test/test_model_moebius.py
cva/test/test_model_sphere.py
cva/test/test_model_sphylinder.py
cva/test/test_model_tilted_plane.py
cva/test/test_model_torus.py
cva/test/test_model_vertical_plane.py
cva/test/test_solve_brachistochrone_unit_sphere.py
cva/test/test_solve_cylinder.py
cva/test/test_solve_earth.py
cva/test/test_solve_earth_wraparound.py
cva/test/test_solve_hyperboloid.py
cva/test/test_solve_nsphere_r3.py
cva/test/test_solve_nsphere_r4.py
cva/test/test_solve_nsphere_r5.py
cva/test/test_solve_refine.py
cva/test/test_solve_sphere.py
