Metadata-Version: 1.1
Name: cva
Version: 0.9.4
Summary: Calculus of Variations Solver
Home-page: http://github.com/robertjw/
Author: Robert Whitinger
Author-email: cva_account@wmkt.com
License: LGPLv2
Download-URL: http://github.com/robertjw/
Keywords: calculus,variations,functional,analysis
Platform: UNKNOWN
Classifier: Development Status :: 3 - Alpha
Classifier: Intended Audience :: Education
Classifier: Intended Audience :: Science/Research
Classifier: Natural Language :: English
Classifier: License :: OSI Approved :: GNU Lesser General Public License v2 (LGPLv2)
Classifier: Operating System :: OS Independent
Classifier: Programming Language :: Python
Classifier: Programming Language :: Python :: 2.7
Classifier: Programming Language :: Python :: 3.5
Classifier: Topic :: Scientific/Engineering :: Mathematics
